Metadata-Version: 2.1
Name: ndn-python-database
Version: 0.2.11
Summary: An NDN Storage Library for Applications in Python 3
Home-page: https://github.com/tntech-ngin/ndn-python-database
Download-URL: https://pypi.python.org/pypi/ndn-python-database
Author: See GitHub
Author-email: sshannigrahi@tntech.edu
Maintainer: see GitHub
Maintainer-email: sshannigrahi@tntech.edu
License: Apache License 2.0
Project-URL: Bug Tracker, https://github.com/tntech-ngin/ndn-python-database/issues
Project-URL: Source Code, https://github.com/tntech-ngin/ndn-python-database
Keywords: NDN STORAGE DISK MEMORY CACHE
Classifier: Development Status :: 4 - Beta
Classifier: Intended Audience :: Developers
Classifier: Topic :: Software Development :: Libraries
Classifier: Topic :: Internet
Classifier: Topic :: System :: Networking
Classifier: License :: OSI Approved :: Apache Software License
Classifier: Programming Language :: Python :: 3.8
Classifier: Programming Language :: Python :: 3.9
Classifier: Programming Language :: Python :: 3.10
Requires-Python: >=3.8
License-File: LICENSE.rst
License-File: AUTHORS.rst
Requires-Dist: plyvel >=1.4.0
Requires-Dist: pymongo >=4.0.1
Requires-Dist: python-ndn >=0.4.1
